{
    "stock_code": "090470",
    "date": "20250711",
    "start_date": "20250711",
    "end_date": "20250711",
    "data_count": 36,
    "collection_settings": {
        "start_time": "09:00",
        "end_time": "15:30",
        "interval_minutes": 10
    },
    "data": [
        {
            "localDateTime": "20250711090000",
            "currentPrice": 3680.0,
            "openPrice": 3625.0,
            "highPrice": 3680.0,
            "lowPrice": 3625.0,
            "accumulatedTradingVolume": 484
        },
        {
            "localDateTime": "20250711091000",
            "currentPrice": 3680.0,
            "openPrice": 3675.0,
            "highPrice": 3685.0,
            "lowPrice": 3670.0,
            "accumulatedTradingVolume": 1013
        },
        {
            "localDateTime": "20250711092000",
            "currentPrice": 3675.0,
            "openPrice": 3675.0,
            "highPrice": 3675.0,
            "lowPrice": 3655.0,
            "accumulatedTradingVolume": 272
        },
        {
            "localDateTime": "20250711093000",
            "currentPrice": 3655.0,
            "openPrice": 3660.0,
            "highPrice": 3665.0,
            "lowPrice": 3625.0,
            "accumulatedTradingVolume": 1439
        },
        {
            "localDateTime": "20250711094000",
            "currentPrice": 3670.0,
            "openPrice": 3660.0,
            "highPrice": 3670.0,
            "lowPrice": 3660.0,
            "accumulatedTradingVolume": 773
        },
        {
            "localDateTime": "20250711095000",
            "currentPrice": 3680.0,
            "openPrice": 3670.0,
            "highPrice": 3680.0,
            "lowPrice": 3670.0,
            "accumulatedTradingVolume": 508
        },
        {
            "localDateTime": "20250711100000",
            "currentPrice": 3680.0,
            "openPrice": 3680.0,
            "highPrice": 3680.0,
            "lowPrice": 3655.0,
            "accumulatedTradingVolume": 681
        },
        {
            "localDateTime": "20250711101000",
            "currentPrice": 3680.0,
            "openPrice": 3675.0,
            "highPrice": 3680.0,
            "lowPrice": 3670.0,
            "accumulatedTradingVolume": 951
        },
        {
            "localDateTime": "20250711102000",
            "currentPrice": 3700.0,
            "openPrice": 3675.0,
            "highPrice": 3710.0,
            "lowPrice": 3675.0,
            "accumulatedTradingVolume": 4141
        },
        {
            "localDateTime": "20250711103000",
            "currentPrice": 3715.0,
            "openPrice": 3700.0,
            "highPrice": 3715.0,
            "lowPrice": 3700.0,
            "accumulatedTradingVolume": 1091
        },
        {
            "localDateTime": "20250711104000",
            "currentPrice": 3720.0,
            "openPrice": 3715.0,
            "highPrice": 3720.0,
            "lowPrice": 3710.0,
            "accumulatedTradingVolume": 330
        },
        {
            "localDateTime": "20250711105000",
            "currentPrice": 3710.0,
            "openPrice": 3720.0,
            "highPrice": 3720.0,
            "lowPrice": 3710.0,
            "accumulatedTradingVolume": 559
        },
        {
            "localDateTime": "20250711110000",
            "currentPrice": 3725.0,
            "openPrice": 3715.0,
            "highPrice": 3730.0,
            "lowPrice": 3715.0,
            "accumulatedTradingVolume": 366
        },
        {
            "localDateTime": "20250711111000",
            "currentPrice": 3720.0,
            "openPrice": 3720.0,
            "highPrice": 3720.0,
            "lowPrice": 3720.0,
            "accumulatedTradingVolume": 650
        },
        {
            "localDateTime": "20250711112000",
            "currentPrice": 3710.0,
            "openPrice": 3725.0,
            "highPrice": 3725.0,
            "lowPrice": 3710.0,
            "accumulatedTradingVolume": 352
        },
        {
            "localDateTime": "20250711113000",
            "currentPrice": 3710.0,
            "openPrice": 3710.0,
            "highPrice": 3710.0,
            "lowPrice": 3700.0,
            "accumulatedTradingVolume": 235
        },
        {
            "localDateTime": "20250711114000",
            "currentPrice": 3730.0,
            "openPrice": 3715.0,
            "highPrice": 3730.0,
            "lowPrice": 3715.0,
            "accumulatedTradingVolume": 1381
        },
        {
            "localDateTime": "20250711115000",
            "currentPrice": 3715.0,
            "openPrice": 3730.0,
            "highPrice": 3730.0,
            "lowPrice": 3715.0,
            "accumulatedTradingVolume": 775
        },
        {
            "localDateTime": "20250711120000",
            "currentPrice": 3730.0,
            "openPrice": 3720.0,
            "highPrice": 3730.0,
            "lowPrice": 3720.0,
            "accumulatedTradingVolume": 254
        },
        {
            "localDateTime": "20250711121000",
            "currentPrice": 3730.0,
            "openPrice": 3725.0,
            "highPrice": 3730.0,
            "lowPrice": 3725.0,
            "accumulatedTradingVolume": 3
        },
        {
            "localDateTime": "20250711122000",
            "currentPrice": 3735.0,
            "openPrice": 3730.0,
            "highPrice": 3735.0,
            "lowPrice": 3730.0,
            "accumulatedTradingVolume": 549
        },
        {
            "localDateTime": "20250711123000",
            "currentPrice": 3730.0,
            "openPrice": 3740.0,
            "highPrice": 3740.0,
            "lowPrice": 3730.0,
            "accumulatedTradingVolume": 478
        },
        {
            "localDateTime": "20250711124000",
            "currentPrice": 3720.0,
            "openPrice": 3730.0,
            "highPrice": 3730.0,
            "lowPrice": 3720.0,
            "accumulatedTradingVolume": 315
        },
        {
            "localDateTime": "20250711125000",
            "currentPrice": 3725.0,
            "openPrice": 3720.0,
            "highPrice": 3725.0,
            "lowPrice": 3720.0,
            "accumulatedTradingVolume": 151
        },
        {
            "localDateTime": "20250711131000",
            "currentPrice": 3730.0,
            "openPrice": 3725.0,
            "highPrice": 3730.0,
            "lowPrice": 3725.0,
            "accumulatedTradingVolume": 329
        },
        {
            "localDateTime": "20250711132000",
            "currentPrice": 3705.0,
            "openPrice": 3730.0,
            "highPrice": 3730.0,
            "lowPrice": 3705.0,
            "accumulatedTradingVolume": 23
        },
        {
            "localDateTime": "20250711133000",
            "currentPrice": 3710.0,
            "openPrice": 3705.0,
            "highPrice": 3710.0,
            "lowPrice": 3690.0,
            "accumulatedTradingVolume": 202
        },
        {
            "localDateTime": "20250711134000",
            "currentPrice": 3710.0,
            "openPrice": 3695.0,
            "highPrice": 3710.0,
            "lowPrice": 3695.0,
            "accumulatedTradingVolume": 2
        },
        {
            "localDateTime": "20250711140000",
            "currentPrice": 3710.0,
            "openPrice": 3695.0,
            "highPrice": 3710.0,
            "lowPrice": 3695.0,
            "accumulatedTradingVolume": 216
        },
        {
            "localDateTime": "20250711141000",
            "currentPrice": 3700.0,
            "openPrice": 3700.0,
            "highPrice": 3700.0,
            "lowPrice": 3700.0,
            "accumulatedTradingVolume": 4
        },
        {
            "localDateTime": "20250711142000",
            "currentPrice": 3700.0,
            "openPrice": 3700.0,
            "highPrice": 3700.0,
            "lowPrice": 3700.0,
            "accumulatedTradingVolume": 147
        },
        {
            "localDateTime": "20250711143000",
            "currentPrice": 3695.0,
            "openPrice": 3700.0,
            "highPrice": 3700.0,
            "lowPrice": 3695.0,
            "accumulatedTradingVolume": 169
        },
        {
            "localDateTime": "20250711144000",
            "currentPrice": 3700.0,
            "openPrice": 3695.0,
            "highPrice": 3700.0,
            "lowPrice": 3695.0,
            "accumulatedTradingVolume": 152
        },
        {
            "localDateTime": "20250711145000",
            "currentPrice": 3705.0,
            "openPrice": 3705.0,
            "highPrice": 3710.0,
            "lowPrice": 3705.0,
            "accumulatedTradingVolume": 1900
        },
        {
            "localDateTime": "20250711151000",
            "currentPrice": 3720.0,
            "openPrice": 3705.0,
            "highPrice": 3720.0,
            "lowPrice": 3705.0,
            "accumulatedTradingVolume": 543
        },
        {
            "localDateTime": "20250711153000",
            "currentPrice": 3700.0,
            "openPrice": 3700.0,
            "highPrice": 3700.0,
            "lowPrice": 3700.0,
            "accumulatedTradingVolume": 550
        }
    ]
}