{
    "stock_code": "100590",
    "date": "20250722",
    "rsi_period": 14,
    "data_count": 38,
    "calculation_settings": {
        "rsi_period": 14,
        "calculation_method": "exponential_moving_average",
        "previous_data_used": true
    },
    "data": [
        {
            "localDateTime": "20250722090000",
            "currentPrice": 3395.0,
            "rsi": 53.0120481927711,
            "rsi_period": 14
        },
        {
            "localDateTime": "20250722091000",
            "currentPrice": 3405.0,
            "rsi": 53.0120481927711,
            "rsi_period": 14
        },
        {
            "localDateTime": "20250722092000",
            "currentPrice": 3405.0,
            "rsi": 53.01204819277108,
            "rsi_period": 14
        },
        {
            "localDateTime": "20250722093000",
            "currentPrice": 3405.0,
            "rsi": 49.53362176306517,
            "rsi_period": 14
        },
        {
            "localDateTime": "20250722094000",
            "currentPrice": 3400.0,
            "rsi": 49.53362176306516,
            "rsi_period": 14
        },
        {
            "localDateTime": "20250722095000",
            "currentPrice": 3400.0,
            "rsi": 42.990564144295675,
            "rsi_period": 14
        },
        {
            "localDateTime": "20250722100000",
            "currentPrice": 3390.0,
            "rsi": 50.090416109642064,
            "rsi_period": 14
        },
        {
            "localDateTime": "20250722101000",
            "currentPrice": 3400.0,
            "rsi": 55.992602491955445,
            "rsi_period": 14
        },
        {
            "localDateTime": "20250722102000",
            "currentPrice": 3410.0,
            "rsi": 55.992602491955445,
            "rsi_period": 14
        },
        {
            "localDateTime": "20250722103000",
            "currentPrice": 3410.0,
            "rsi": 55.992602491955445,
            "rsi_period": 14
        },
        {
            "localDateTime": "20250722104000",
            "currentPrice": 3410.0,
            "rsi": 52.1419007304784,
            "rsi_period": 14
        },
        {
            "localDateTime": "20250722105000",
            "currentPrice": 3405.0,
            "rsi": 45.41488925515116,
            "rsi_period": 14
        },
        {
            "localDateTime": "20250722110000",
            "currentPrice": 3395.0,
            "rsi": 45.41488925515116,
            "rsi_period": 14
        },
        {
            "localDateTime": "20250722111000",
            "currentPrice": 3395.0,
            "rsi": 45.41488925515116,
            "rsi_period": 14
        },
        {
            "localDateTime": "20250722112000",
            "currentPrice": 3395.0,
            "rsi": 42.02874261423157,
            "rsi_period": 14
        },
        {
            "localDateTime": "20250722113000",
            "currentPrice": 3390.0,
            "rsi": 46.33760144899694,
            "rsi_period": 14
        },
        {
            "localDateTime": "20250722114000",
            "currentPrice": 3395.0,
            "rsi": 39.94310885368885,
            "rsi_period": 14
        },
        {
            "localDateTime": "20250722115000",
            "currentPrice": 3385.0,
            "rsi": 44.09706436787096,
            "rsi_period": 14
        },
        {
            "localDateTime": "20250722120000",
            "currentPrice": 3390.0,
            "rsi": 41.04008878985487,
            "rsi_period": 14
        },
        {
            "localDateTime": "20250722121000",
            "currentPrice": 3385.0,
            "rsi": 38.18903348965135,
            "rsi_period": 14
        },
        {
            "localDateTime": "20250722122000",
            "currentPrice": 3380.0,
            "rsi": 38.18903348965136,
            "rsi_period": 14
        },
        {
            "localDateTime": "20250722123000",
            "currentPrice": 3380.0,
            "rsi": 38.18903348965135,
            "rsi_period": 14
        },
        {
            "localDateTime": "20250722124000",
            "currentPrice": 3380.0,
            "rsi": 43.12396063657397,
            "rsi_period": 14
        },
        {
            "localDateTime": "20250722125000",
            "currentPrice": 3385.0,
            "rsi": 39.7097012340572,
            "rsi_period": 14
        },
        {
            "localDateTime": "20250722130000",
            "currentPrice": 3380.0,
            "rsi": 26.27032212587673,
            "rsi_period": 14
        },
        {
            "localDateTime": "20250722131000",
            "currentPrice": 3350.0,
            "rsi": 30.492602296468007,
            "rsi_period": 14
        },
        {
            "localDateTime": "20250722132000",
            "currentPrice": 3355.0,
            "rsi": 38.124587151838355,
            "rsi_period": 14
        },
        {
            "localDateTime": "20250722133000",
            "currentPrice": 3365.0,
            "rsi": 35.99635183196068,
            "rsi_period": 14
        },
        {
            "localDateTime": "20250722134000",
            "currentPrice": 3360.0,
            "rsi": 35.99635183196068,
            "rsi_period": 14
        },
        {
            "localDateTime": "20250722135000",
            "currentPrice": 3360.0,
            "rsi": 33.80759203647297,
            "rsi_period": 14
        },
        {
            "localDateTime": "20250722140000",
            "currentPrice": 3355.0,
            "rsi": 28.256654992335243,
            "rsi_period": 14
        },
        {
            "localDateTime": "20250722141000",
            "currentPrice": 3340.0,
            "rsi": 28.256654992335243,
            "rsi_period": 14
        },
        {
            "localDateTime": "20250722142000",
            "currentPrice": 3340.0,
            "rsi": 52.41843346190322,
            "rsi_period": 14
        },
        {
            "localDateTime": "20250722143000",
            "currentPrice": 3380.0,
            "rsi": 44.37188167994038,
            "rsi_period": 14
        },
        {
            "localDateTime": "20250722144000",
            "currentPrice": 3360.0,
            "rsi": 46.579668046021354,
            "rsi_period": 14
        },
        {
            "localDateTime": "20250722145000",
            "currentPrice": 3365.0,
            "rsi": 41.28584097063662,
            "rsi_period": 14
        },
        {
            "localDateTime": "20250722150000",
            "currentPrice": 3350.0,
            "rsi": 49.52320980173595,
            "rsi_period": 14
        },
        {
            "localDateTime": "20250722151000",
            "currentPrice": 3370.0,
            "rsi": 46.04479851270306,
            "rsi_period": 14
        }
    ]
}