{
    "stock_code": "395400",
    "date": "20250716",
    "start_date": "20250716",
    "end_date": "20250716",
    "data_count": 39,
    "collection_settings": {
        "start_time": "09:00",
        "end_time": "15:30",
        "interval_minutes": 10
    },
    "data": [
        {
            "localDateTime": "20250716090000",
            "currentPrice": 4720.0,
            "openPrice": 4745.0,
            "highPrice": 4745.0,
            "lowPrice": 4710.0,
            "accumulatedTradingVolume": 6421
        },
        {
            "localDateTime": "20250716091000",
            "currentPrice": 4720.0,
            "openPrice": 4720.0,
            "highPrice": 4725.0,
            "lowPrice": 4715.0,
            "accumulatedTradingVolume": 2953
        },
        {
            "localDateTime": "20250716092000",
            "currentPrice": 4705.0,
            "openPrice": 4720.0,
            "highPrice": 4720.0,
            "lowPrice": 4705.0,
            "accumulatedTradingVolume": 15965
        },
        {
            "localDateTime": "20250716093000",
            "currentPrice": 4745.0,
            "openPrice": 4715.0,
            "highPrice": 4745.0,
            "lowPrice": 4710.0,
            "accumulatedTradingVolume": 6291
        },
        {
            "localDateTime": "20250716094000",
            "currentPrice": 4720.0,
            "openPrice": 4740.0,
            "highPrice": 4740.0,
            "lowPrice": 4720.0,
            "accumulatedTradingVolume": 1013
        },
        {
            "localDateTime": "20250716095000",
            "currentPrice": 4745.0,
            "openPrice": 4720.0,
            "highPrice": 4745.0,
            "lowPrice": 4715.0,
            "accumulatedTradingVolume": 4360
        },
        {
            "localDateTime": "20250716100000",
            "currentPrice": 4735.0,
            "openPrice": 4745.0,
            "highPrice": 4745.0,
            "lowPrice": 4715.0,
            "accumulatedTradingVolume": 1585
        },
        {
            "localDateTime": "20250716101000",
            "currentPrice": 4730.0,
            "openPrice": 4735.0,
            "highPrice": 4740.0,
            "lowPrice": 4715.0,
            "accumulatedTradingVolume": 5556
        },
        {
            "localDateTime": "20250716102000",
            "currentPrice": 4725.0,
            "openPrice": 4735.0,
            "highPrice": 4735.0,
            "lowPrice": 4715.0,
            "accumulatedTradingVolume": 1680
        },
        {
            "localDateTime": "20250716103000",
            "currentPrice": 4705.0,
            "openPrice": 4725.0,
            "highPrice": 4725.0,
            "lowPrice": 4705.0,
            "accumulatedTradingVolume": 12496
        },
        {
            "localDateTime": "20250716104000",
            "currentPrice": 4705.0,
            "openPrice": 4720.0,
            "highPrice": 4720.0,
            "lowPrice": 4705.0,
            "accumulatedTradingVolume": 2499
        },
        {
            "localDateTime": "20250716105000",
            "currentPrice": 4710.0,
            "openPrice": 4705.0,
            "highPrice": 4710.0,
            "lowPrice": 4700.0,
            "accumulatedTradingVolume": 15892
        },
        {
            "localDateTime": "20250716110000",
            "currentPrice": 4710.0,
            "openPrice": 4705.0,
            "highPrice": 4715.0,
            "lowPrice": 4705.0,
            "accumulatedTradingVolume": 7150
        },
        {
            "localDateTime": "20250716111000",
            "currentPrice": 4710.0,
            "openPrice": 4710.0,
            "highPrice": 4715.0,
            "lowPrice": 4705.0,
            "accumulatedTradingVolume": 4907
        },
        {
            "localDateTime": "20250716112000",
            "currentPrice": 4715.0,
            "openPrice": 4710.0,
            "highPrice": 4715.0,
            "lowPrice": 4700.0,
            "accumulatedTradingVolume": 14391
        },
        {
            "localDateTime": "20250716113000",
            "currentPrice": 4705.0,
            "openPrice": 4715.0,
            "highPrice": 4715.0,
            "lowPrice": 4700.0,
            "accumulatedTradingVolume": 9147
        },
        {
            "localDateTime": "20250716114000",
            "currentPrice": 4715.0,
            "openPrice": 4710.0,
            "highPrice": 4715.0,
            "lowPrice": 4700.0,
            "accumulatedTradingVolume": 4656
        },
        {
            "localDateTime": "20250716115000",
            "currentPrice": 4705.0,
            "openPrice": 4710.0,
            "highPrice": 4725.0,
            "lowPrice": 4705.0,
            "accumulatedTradingVolume": 14359
        },
        {
            "localDateTime": "20250716120000",
            "currentPrice": 4715.0,
            "openPrice": 4705.0,
            "highPrice": 4720.0,
            "lowPrice": 4705.0,
            "accumulatedTradingVolume": 4417
        },
        {
            "localDateTime": "20250716121000",
            "currentPrice": 4710.0,
            "openPrice": 4705.0,
            "highPrice": 4720.0,
            "lowPrice": 4705.0,
            "accumulatedTradingVolume": 3323
        },
        {
            "localDateTime": "20250716122000",
            "currentPrice": 4715.0,
            "openPrice": 4710.0,
            "highPrice": 4715.0,
            "lowPrice": 4705.0,
            "accumulatedTradingVolume": 3651
        },
        {
            "localDateTime": "20250716123000",
            "currentPrice": 4700.0,
            "openPrice": 4710.0,
            "highPrice": 4715.0,
            "lowPrice": 4700.0,
            "accumulatedTradingVolume": 8245
        },
        {
            "localDateTime": "20250716124000",
            "currentPrice": 4710.0,
            "openPrice": 4700.0,
            "highPrice": 4715.0,
            "lowPrice": 4700.0,
            "accumulatedTradingVolume": 4629
        },
        {
            "localDateTime": "20250716125000",
            "currentPrice": 4715.0,
            "openPrice": 4705.0,
            "highPrice": 4715.0,
            "lowPrice": 4700.0,
            "accumulatedTradingVolume": 2802
        },
        {
            "localDateTime": "20250716130000",
            "currentPrice": 4715.0,
            "openPrice": 4710.0,
            "highPrice": 4715.0,
            "lowPrice": 4705.0,
            "accumulatedTradingVolume": 3696
        },
        {
            "localDateTime": "20250716131000",
            "currentPrice": 4710.0,
            "openPrice": 4715.0,
            "highPrice": 4715.0,
            "lowPrice": 4705.0,
            "accumulatedTradingVolume": 2894
        },
        {
            "localDateTime": "20250716132000",
            "currentPrice": 4715.0,
            "openPrice": 4715.0,
            "highPrice": 4715.0,
            "lowPrice": 4710.0,
            "accumulatedTradingVolume": 1962
        },
        {
            "localDateTime": "20250716133000",
            "currentPrice": 4720.0,
            "openPrice": 4710.0,
            "highPrice": 4720.0,
            "lowPrice": 4710.0,
            "accumulatedTradingVolume": 6818
        },
        {
            "localDateTime": "20250716134000",
            "currentPrice": 4720.0,
            "openPrice": 4720.0,
            "highPrice": 4725.0,
            "lowPrice": 4715.0,
            "accumulatedTradingVolume": 3803
        },
        {
            "localDateTime": "20250716135000",
            "currentPrice": 4750.0,
            "openPrice": 4725.0,
            "highPrice": 4755.0,
            "lowPrice": 4715.0,
            "accumulatedTradingVolume": 30216
        },
        {
            "localDateTime": "20250716140000",
            "currentPrice": 4745.0,
            "openPrice": 4745.0,
            "highPrice": 4745.0,
            "lowPrice": 4735.0,
            "accumulatedTradingVolume": 12356
        },
        {
            "localDateTime": "20250716141000",
            "currentPrice": 4745.0,
            "openPrice": 4745.0,
            "highPrice": 4755.0,
            "lowPrice": 4735.0,
            "accumulatedTradingVolume": 17212
        },
        {
            "localDateTime": "20250716142000",
            "currentPrice": 4760.0,
            "openPrice": 4745.0,
            "highPrice": 4760.0,
            "lowPrice": 4740.0,
            "accumulatedTradingVolume": 12481
        },
        {
            "localDateTime": "20250716143000",
            "currentPrice": 4740.0,
            "openPrice": 4765.0,
            "highPrice": 4765.0,
            "lowPrice": 4740.0,
            "accumulatedTradingVolume": 14314
        },
        {
            "localDateTime": "20250716144000",
            "currentPrice": 4730.0,
            "openPrice": 4745.0,
            "highPrice": 4755.0,
            "lowPrice": 4725.0,
            "accumulatedTradingVolume": 14507
        },
        {
            "localDateTime": "20250716145000",
            "currentPrice": 4745.0,
            "openPrice": 4730.0,
            "highPrice": 4745.0,
            "lowPrice": 4730.0,
            "accumulatedTradingVolume": 13386
        },
        {
            "localDateTime": "20250716150000",
            "currentPrice": 4735.0,
            "openPrice": 4740.0,
            "highPrice": 4740.0,
            "lowPrice": 4720.0,
            "accumulatedTradingVolume": 15240
        },
        {
            "localDateTime": "20250716151000",
            "currentPrice": 4705.0,
            "openPrice": 4735.0,
            "highPrice": 4745.0,
            "lowPrice": 4705.0,
            "accumulatedTradingVolume": 26933
        },
        {
            "localDateTime": "20250716153000",
            "currentPrice": 4705.0,
            "openPrice": 4705.0,
            "highPrice": 4705.0,
            "lowPrice": 4705.0,
            "accumulatedTradingVolume": 8836
        }
    ]
}